iclick/__init__.py
iclick/event.py
iclick/utils.py
iclick_auto-1.0.1.dist-info/LICENSE
iclick_auto-1.0.1.dist-info/METADATA
iclick_auto-1.0.1.dist-info/WHEEL
iclick_auto-1.0.1.dist-info/top_level.txt
iclick_auto-1.0.1.dist-info/RECORD
