Metadata-Version: 2.1
Name: iclick-auto
Version: 1.0.1
Summary: iClick Automation Tool Without Jailbreak Python Package.
Home-page: https://github.com/Undefined-Token/iclick-python
Author: iClick
Author-email: iClick <try.catch@foxmail.com>
License: MIT
Project-URL: Homepage, https://github.com/Undefined-Token/iclick-python
Project-URL: Repository, https://github.com/Undefined-Token/iclick-python
Project-URL: Issues, https://github.com/Undefined-Token/iclick-python/issues
Keywords: IOS,Automation,Without Jailbreak
Classifier: Development Status :: 4 - Beta
Classifier: Intended Audience :: Developers
Classifier: License :: OSI Approved :: MIT License
Classifier: Programming Language :: Python :: 3
Classifier: Programming Language :: Python :: 3.7
Classifier: Programming Language :: Python :: 3.8
Classifier: Programming Language :: Python :: 3.9
Classifier: Programming Language :: Python :: 3.10
Classifier: Programming Language :: Python :: 3.11
Requires-Python: >=3.7
License-File: LICENSE
Requires-Dist: websocket-client>=1.6.0
